<?xml version="1.0" encoding="UTF-8"?>
<tv generator-info-name="WebGrab+Plus/w MDB &amp; REX Postprocess -- version V2.1.11.0 -- Jan van Straaten" generator-info-url="http://www.webgrabplus.com">
  <channel id="OndaCadiz.TDTChannelsEPG">
    <display-name lang="es">Onda Cádiz</display-name>
    <url>http://www.pyTDTChannels</url>
  </channel>
  <programme start="20200122020000 +0100" stop="20200122040000 +0100" channel="OndaCadiz.TDTChannelsEPG">
    <title lang="es">El mirador - noticias</title>
    <desc lang="es">Primera parte del Magazine el Mirador con un marcado carácter informativo.
La iniciamos asomándonos a la previsión meteorológica y a las portadas del día de los principales periódicos locales y nacionales, para seguidamente repasar las noticias más destacadas ofrecidas por los servicios informativos de Onda Cádiz Tv.
A continuación, espacio para el Debate y el intercambio de opiniones e ideas en la  tertulia de actualidad. Sociedad, política, economía, cultura, costumbres y demás aspectos de interés con la mirada puesta principalmente en las cuestiones que más afectan a nuestra capital, nuestra Bahía y nuestra provincia.
Esta primera parte del Mirador se remata con una encuentro con las Instituciones públicas, Colegios profesionales, asociaciones del ámbito de la  empresa, Universidad, Cuerpos y Fuerzas Seguridad y demás organismos públicos y privados en una entrevista de actualidad.</desc>
    <icon src="http://tv.ocadizdigital.es/sites/default/files/styles/ancho-350/public/imagenes_programas/logo_el_mirador_boton_noticias.jpg?itok=i43Wib16" />
  </programme>
  <programme start="20200122040000 +0100" stop="20200122043000 +0100" channel="OndaCadiz.TDTChannelsEPG">
    <title lang="es">Saludablemente</title>
    <desc lang="es">Onda Cádiz televisión estrena programa sobre Salud y Bienestar.
“Saludablemente” es un nuevo espacio con reportajes y entrevistas en distinto formato con el objetivo de aportar opciones para mejorar la calidad de vida de nuestros televidentes.
Contaremos con profesionales acreditados para aportar sus conocimientos y valoraciones. Secciones como “Tecnologías para la Salud”, “Actualidad”, “Sexo y Salud”, “Mente Sana”, “Nutrición” y “Ocio Saludable” irán añadiendo contenidos de interés, en un espacio con una hora de duración.
“Saludablemente” estará en sus casas a través de su televisión municipal cada semana, los sábados a las 21:30 horas, conducido por la periodista y redactora de informativos de esta casa, Fátima Sánchez.</desc>
    <icon src="http://tv.ocadizdigital.es/sites/default/files/styles/ancho-350/public/imagenes_programas/saludablemente_logo.jpg?itok=cyhfz8yd" />
  </programme>
  <programme start="20200122043000 +0100" stop="20200122073000 +0100" channel="OndaCadiz.TDTChannelsEPG">
    <title lang="es">Fin emisión</title>
    <icon src="http://tv.ocadizdigital.es/sites/default/files/styles/ancho-350/public/imagenes_programas/ondacadiz_logo-1escalado_3.png?itok=V3zle7Kq" />
  </programme>
  <programme start="20200122073000 +0100" stop="20200122090000 +0100" channel="OndaCadiz.TDTChannelsEPG">
    <title lang="es">Las ma\u00f1anas del Falla</title>
    <icon src="https://carnavaldecadiztv.com/wp-content/uploads/2019/08/coac-2020.jpg" />
  </programme>
  <programme start="20200122090000 +0100" stop="20200122103000 +0100" channel="OndaCadiz.TDTChannelsEPG">
    <title lang="es">El mirador - noticias</title>
    <desc lang="es">Primera parte del Magazine el Mirador con un marcado carácter informativo.
La iniciamos asomándonos a la previsión meteorológica y a las portadas del día de los principales periódicos locales y nacionales, para seguidamente repasar las noticias más destacadas ofrecidas por los servicios informativos de Onda Cádiz Tv.
A continuación, espacio para el Debate y el intercambio de opiniones e ideas en la  tertulia de actualidad. Sociedad, política, economía, cultura, costumbres y demás aspectos de interés con la mirada puesta principalmente en las cuestiones que más afectan a nuestra capital, nuestra Bahía y nuestra provincia.
Esta primera parte del Mirador se remata con una encuentro con las Instituciones públicas, Colegios profesionales, asociaciones del ámbito de la  empresa, Universidad, Cuerpos y Fuerzas Seguridad y demás organismos públicos y privados en una entrevista de actualidad.</desc>
    <icon src="http://tv.ocadizdigital.es/sites/default/files/styles/ancho-350/public/imagenes_programas/logo_el_mirador_boton_noticias.jpg?itok=i43Wib16" />
  </programme>
  <programme start="20200122103000 +0100" stop="20200122110000 +0100" channel="OndaCadiz.TDTChannelsEPG">
    <title lang="es">El mirador - social</title>
    <desc lang="es">Enrique Miranda y Anabel Flores les invitan a este espacio de entretenimiento de dos horas en directo dedicado a la actualidad y eventos destacados en la ciudad. Música, moda, espectáculos, flamenco, gastronomía, asociaciones y entidades solidarias visitarán nuestro plató para compartir sus proyectos. Asómense al Mirador Magazine para descubrir Cádiz y su faceta más artística y cultural.</desc>
    <icon src="http://tv.ocadizdigital.es/sites/default/files/styles/ancho-350/public/imagenes_programas/logo_el_mirador_boton_social.jpg?itok=d7lUUMa8" />
  </programme>
  <programme start="20200122110000 +0100" stop="20200122113000 +0100" channel="OndaCadiz.TDTChannelsEPG">
    <title lang="es">La levantá</title>
    <desc lang="es">Programa dedicado en exclusividad a la Semana Santa gaditana y todo lo relacionado con la misma. Hermandades y Cofradías, salidas procesionales, cultos y distintas actividades, son tratados en formatos de entrevistas, tertulias y reportajes. Mayte Huguet es el encargo de dar forma a este espacio televisivo.</desc>
    <icon src="http://tv.ocadizdigital.es/sites/default/files/styles/ancho-350/public/imagenes_programas/la_levanta.jpg?itok=j694IFE6" />
  </programme>
  <programme start="20200122113000 +0100" stop="20200122130000 +0100" channel="OndaCadiz.TDTChannelsEPG">
    <title lang="es">Las ma\u00f1anas del Falla</title>
    <icon src="https://carnavaldecadiztv.com/wp-content/uploads/2019/08/coac-2020.jpg" />
  </programme>
  <programme start="20200122130000 +0100" stop="20200122133000 +0100" channel="OndaCadiz.TDTChannelsEPG">
    <title lang="es">Carnaval a\u00f1ejo</title>
    <icon src="https://carnavaldecadiztv.com/wp-content/uploads/2019/08/coac-2020.jpg" />
  </programme>
  <programme start="20200122133000 +0100" stop="20200122140000 +0100" channel="OndaCadiz.TDTChannelsEPG">
    <title lang="es">Noticias OC 1ª Edición</title>
    <desc lang="es">Desde Onda Cádiz Televisión, ofrecemos a nuestros espectadores, la posibilidad de que puedan tomar, con nosotros, el pulso diario de nuestra ciudad. Política, cultura, sucesos, ocio, deportes, información meteorológica y toda la información puntual que genera nuestra ciudad, con el máximo rigor y pluralidad que debe de tener una televisión municipal.</desc>
    <icon src="http://tv.ocadizdigital.es/sites/default/files/styles/ancho-350/public/imagenes_programas/noticias_cadiz.jpg?itok=N_oSD2Vc" />
  </programme>
  <programme start="20200122140000 +0100" stop="20200122190000 +0100" channel="OndaCadiz.TDTChannelsEPG">
    <title lang="es">COAC 2020</title>
    <desc lang="es">Comparsa El Alcalde 
J. Manuel Armuña, Manuel Alonso, Raúl Ruiz y Antonio José Durán (Granada)

Cuarteto Vida y obra de Juan Carlos | Bajode 
Ángel Gago, Miguel Ángel Moreno y José Manuel Cossio – En 2019: Cuarteto Este año nos retiramos

Chirigota No te gusta ná José 
Miguel Choza – En 2019: Los Cabronissimos (Cádiz)

Comparsa 4 de diciembre 
J. Luis Torres – El Puerto de Santamaría

Chirigota Los viejos del parque 
J. Francisco Castro y David Castro – Écija

Comparsa El Gran Dictador 
Juanma Hernández y Dani Montiel – Nueva Agrupación (Sevilla)

Comparsa Érase una vez… 
Montserat Mascareña y Ana María Salas – Isla Cristina (Huelva).</desc>
    <icon src="https://carnavaldecadiztv.com/wp-content/uploads/2019/08/coac-2020.jpg" />
  </programme>
  <programme start="20200122190000 +0100" stop="20200122193000 +0100" channel="OndaCadiz.TDTChannelsEPG">
    <title lang="es">Noticias OC</title>
    <desc lang="es">Desde Onda Cádiz Televisión, ofrecemos a nuestros espectadores, la posibilidad de que puedan tomar, con nosotros, el pulso diario de nuestra ciudad. Política, cultura, sucesos, ocio, deportes, información meteorológica y toda la información puntual que genera nuestra ciudad, con el máximo rigor y pluralidad que debe de tener una televisión municipal.</desc>
    <icon src="http://tv.ocadizdigital.es/sites/default/files/styles/ancho-350/public/imagenes_programas/noticias_cadiz.jpg?itok=N_oSD2Vc" />
  </programme>
  <programme start="20200122193000 +0100" stop="20200123010000 +0100" channel="OndaCadiz.TDTChannelsEPG">
    <title lang="es">COAC 2020</title>
    <desc lang="es">Comparsa ¡¡Quieto todo el mundo!! 
Iván Romero – En 2019: ¿Te lo cuento o te lo canto?

Cabeza de serie: Chirigota Los Gipsy Scream 
La agrupación y José María Barrunco ‘El Lacio’ – En 2019 2º premio: Daddy Cadi (Sevilla)

Comparsa Hospital Febrero: 
P. Jesús Ramírez y Álvaro Palacios (Alcalá de Guadaira)

Coro El Fantasma del tablao 
Anselmo García, J. Miguel Pérez, Francisco Molina, Carmelo Tortosa, Leonardo Sacramento, Pedro Pérez, Pablo Caballero, Luis Morilla, J. Manuel Domínguez y Adelino García – Ayamonte (Huelva)

Chirigota Una peli de Comboy Manuel Arauz – Cádiz
Comparsa La divina comparsa 
J. Manuel Marín – Mairena del Alcor

Chirigota Los Hijos del Carota 
J. Manuel Martínez – En 2019: Este año ya me toca a mi (Cádiz).</desc>
    <icon src="https://carnavaldecadiztv.com/wp-content/uploads/2019/08/coac-2020.jpg" />
  </programme>
  <programme start="20200123010000 +0100" stop="20200123013000 +0100" channel="OndaCadiz.TDTChannelsEPG">
    <title lang="es">Noticias OC</title>
    <desc lang="es">Desde Onda Cádiz Televisión, ofrecemos a nuestros espectadores, la posibilidad de que puedan tomar, con nosotros, el pulso diario de nuestra ciudad. Política, cultura, sucesos, ocio, deportes, información meteorológica y toda la información puntual que genera nuestra ciudad, con el máximo rigor y pluralidad que debe de tener una televisión municipal.</desc>
    <icon src="http://tv.ocadizdigital.es/sites/default/files/styles/ancho-350/public/imagenes_programas/noticias_cadiz.jpg?itok=N_oSD2Vc" />
  </programme>
  <programme start="20200123013000 +0100" stop="20200123020000 +0100" channel="OndaCadiz.TDTChannelsEPG">
    <title lang="es">La Buena Educación</title>
    <desc lang="es">La buena educación.</desc>
    <icon src="http://tv.ocadizdigital.es/sites/default/files/styles/ancho-350/public/imagenes_programas/logotipo_la_buena_educacion_boton_tv.jpg?itok=Bcx2Ai6F" />
  </programme>
  <programme start="20200123020000 +0100" stop="20200123040000 +0100" channel="OndaCadiz.TDTChannelsEPG">
    <title lang="es">El mirador - noticias</title>
    <desc lang="es">Primera parte del Magazine el Mirador con un marcado carácter informativo.
La iniciamos asomándonos a la previsión meteorológica y a las portadas del día de los principales periódicos locales y nacionales, para seguidamente repasar las noticias más destacadas ofrecidas por los servicios informativos de Onda Cádiz Tv.
A continuación, espacio para el Debate y el intercambio de opiniones e ideas en la  tertulia de actualidad. Sociedad, política, economía, cultura, costumbres y demás aspectos de interés con la mirada puesta principalmente en las cuestiones que más afectan a nuestra capital, nuestra Bahía y nuestra provincia.
Esta primera parte del Mirador se remata con una encuentro con las Instituciones públicas, Colegios profesionales, asociaciones del ámbito de la  empresa, Universidad, Cuerpos y Fuerzas Seguridad y demás organismos públicos y privados en una entrevista de actualidad.</desc>
    <icon src="http://tv.ocadizdigital.es/sites/default/files/styles/ancho-350/public/imagenes_programas/logo_el_mirador_boton_noticias.jpg?itok=i43Wib16" />
  </programme>
  <programme start="20200123040000 +0100" stop="20200123043000 +0100" channel="OndaCadiz.TDTChannelsEPG">
    <title lang="es">La levantá</title>
    <desc lang="es">Programa dedicado en exclusividad a la Semana Santa gaditana y todo lo relacionado con la misma. Hermandades y Cofradías, salidas procesionales, cultos y distintas actividades, son tratados en formatos de entrevistas, tertulias y reportajes. Mayte Huguet es el encargo de dar forma a este espacio televisivo.</desc>
    <icon src="http://tv.ocadizdigital.es/sites/default/files/styles/ancho-350/public/imagenes_programas/la_levanta.jpg?itok=j694IFE6" />
  </programme>
  <programme start="20200123043000 +0100" stop="20200123073000 +0100" channel="OndaCadiz.TDTChannelsEPG">
    <title lang="es">Fin emisión</title>
    <icon src="http://tv.ocadizdigital.es/sites/default/files/styles/ancho-350/public/imagenes_programas/ondacadiz_logo-1escalado_3.png?itok=V3zle7Kq" />
  </programme>
  <programme start="20200123073000 +0100" stop="20200123090000 +0100" channel="OndaCadiz.TDTChannelsEPG">
    <title lang="es">Las ma\u00f1anas del Falla</title>
    <icon src="https://carnavaldecadiztv.com/wp-content/uploads/2019/08/coac-2020.jpg" />
  </programme>
  <programme start="20200123090000 +0100" stop="20200123103000 +0100" channel="OndaCadiz.TDTChannelsEPG">
    <title lang="es">El mirador - noticias</title>
    <desc lang="es">Primera parte del Magazine el Mirador con un marcado carácter informativo.
La iniciamos asomándonos a la previsión meteorológica y a las portadas del día de los principales periódicos locales y nacionales, para seguidamente repasar las noticias más destacadas ofrecidas por los servicios informativos de Onda Cádiz Tv.
A continuación, espacio para el Debate y el intercambio de opiniones e ideas en la  tertulia de actualidad. Sociedad, política, economía, cultura, costumbres y demás aspectos de interés con la mirada puesta principalmente en las cuestiones que más afectan a nuestra capital, nuestra Bahía y nuestra provincia.
Esta primera parte del Mirador se remata con una encuentro con las Instituciones públicas, Colegios profesionales, asociaciones del ámbito de la  empresa, Universidad, Cuerpos y Fuerzas Seguridad y demás organismos públicos y privados en una entrevista de actualidad.</desc>
    <icon src="http://tv.ocadizdigital.es/sites/default/files/styles/ancho-350/public/imagenes_programas/logo_el_mirador_boton_noticias.jpg?itok=i43Wib16" />
  </programme>
  <programme start="20200123103000 +0100" stop="20200123110000 +0100" channel="OndaCadiz.TDTChannelsEPG">
    <title lang="es">El mirador - social</title>
    <desc lang="es">Enrique Miranda y Anabel Flores les invitan a este espacio de entretenimiento de dos horas en directo dedicado a la actualidad y eventos destacados en la ciudad. Música, moda, espectáculos, flamenco, gastronomía, asociaciones y entidades solidarias visitarán nuestro plató para compartir sus proyectos. Asómense al Mirador Magazine para descubrir Cádiz y su faceta más artística y cultural.</desc>
    <icon src="http://tv.ocadizdigital.es/sites/default/files/styles/ancho-350/public/imagenes_programas/logo_el_mirador_boton_social.jpg?itok=d7lUUMa8" />
  </programme>
  <programme start="20200123110000 +0100" stop="20200123113000 +0100" channel="OndaCadiz.TDTChannelsEPG">
    <title lang="es">Traspunte</title>
    <desc lang="es">Programa de televisión donde hablamos de Cultura, desde la pasión que nos inspiran: la literatura, el teatro, la música, el arte, la danza y todas las disciplinas artísticas que tengan algo que decir en Cádiz. La actualidad y los protagonistas de la agenda cultural, tienen cabida en Traspunte, presentado por Almudena de la Montaña.</desc>
    <icon src="http://tv.ocadizdigital.es/sites/default/files/styles/ancho-350/public/imagenes_programas/traspunte.jpg?itok=y2kTTmMd" />
  </programme>
  <programme start="20200123113000 +0100" stop="20200123130000 +0100" channel="OndaCadiz.TDTChannelsEPG">
    <title lang="es">Las ma\u00f1anas del Falla</title>
    <icon src="https://carnavaldecadiztv.com/wp-content/uploads/2019/08/coac-2020.jpg" />
  </programme>
  <programme start="20200123130000 +0100" stop="20200123133000 +0100" channel="OndaCadiz.TDTChannelsEPG">
    <title lang="es">Carnaval a\u00f1ejo</title>
    <icon src="https://carnavaldecadiztv.com/wp-content/uploads/2019/08/coac-2020.jpg" />
  </programme>
  <programme start="20200123133000 +0100" stop="20200123140000 +0100" channel="OndaCadiz.TDTChannelsEPG">
    <title lang="es">Noticias OC 1ª Edición</title>
    <desc lang="es">Desde Onda Cádiz Televisión, ofrecemos a nuestros espectadores, la posibilidad de que puedan tomar, con nosotros, el pulso diario de nuestra ciudad. Política, cultura, sucesos, ocio, deportes, información meteorológica y toda la información puntual que genera nuestra ciudad, con el máximo rigor y pluralidad que debe de tener una televisión municipal.</desc>
    <icon src="http://tv.ocadizdigital.es/sites/default/files/styles/ancho-350/public/imagenes_programas/noticias_cadiz.jpg?itok=N_oSD2Vc" />
  </programme>
  <programme start="20200123140000 +0100" stop="20200123190000 +0100" channel="OndaCadiz.TDTChannelsEPG">
    <title lang="es">COAC 2020</title>
    <desc lang="es">Comparsa ¡¡Quieto todo el mundo!! 
Iván Romero – En 2019: ¿Te lo cuento o te lo canto?

Cabeza de serie: Chirigota Los Gipsy Scream 
La agrupación y José María Barrunco ‘El Lacio’ – En 2019 2º premio: Daddy Cadi (Sevilla)

Comparsa Hospital Febrero: 
P. Jesús Ramírez y Álvaro Palacios (Alcalá de Guadaira)

Coro El Fantasma del tablao 
Anselmo García, J. Miguel Pérez, Francisco Molina, Carmelo Tortosa, Leonardo Sacramento, Pedro Pérez, Pablo Caballero, Luis Morilla, J. Manuel Domínguez y Adelino García – Ayamonte (Huelva)

Chirigota Una peli de Comboy Manuel Arauz – Cádiz
Comparsa La divina comparsa 
J. Manuel Marín – Mairena del Alcor

Chirigota Los Hijos del Carota 
J. Manuel Martínez – En 2019: Este año ya me toca a mi (Cádiz).</desc>
    <icon src="https://carnavaldecadiztv.com/wp-content/uploads/2019/08/coac-2020.jpg" />
  </programme>
  <programme start="20200123190000 +0100" stop="20200123193000 +0100" channel="OndaCadiz.TDTChannelsEPG">
    <title lang="es">Noticias OC</title>
    <desc lang="es">Desde Onda Cádiz Televisión, ofrecemos a nuestros espectadores, la posibilidad de que puedan tomar, con nosotros, el pulso diario de nuestra ciudad. Política, cultura, sucesos, ocio, deportes, información meteorológica y toda la información puntual que genera nuestra ciudad, con el máximo rigor y pluralidad que debe de tener una televisión municipal.</desc>
    <icon src="http://tv.ocadizdigital.es/sites/default/files/styles/ancho-350/public/imagenes_programas/noticias_cadiz.jpg?itok=N_oSD2Vc" />
  </programme>
  <programme start="20200123193000 +0100" stop="20200124010000 +0100" channel="OndaCadiz.TDTChannelsEPG">
    <title lang="es">COAC 2020</title>
    <desc lang="es">Comparsa Los Caricatos 
Horacio Calvillo – En 2019: La Bella y la Bestia (Ronda)

Comparsa Oh capitán, my capitán 
Constantino Tovar Verdejo – Tercer premio en 2018: Tic-Tac, Tic-Tac (Cádiz)

Cabeza de serie: Coro Las Creaciones S.A. 
Nandi Migueles – En 2019: Ópera Cádiz (Cádiz)

Chirigota El de las llaves con sus muertos 
F. Javier Fuentes – Cádiz

Comparsa La superviviente

Chirigota Las eventuales

Comparsa Los Traicioneros 
L. Miguel Cobos y Marcelo Cobos – En 2019: Los mequetrefes (Córdoba).</desc>
    <icon src="https://carnavaldecadiztv.com/wp-content/uploads/2019/08/coac-2020.jpg" />
  </programme>
  <programme start="20200124010000 +0100" stop="20200124013000 +0100" channel="OndaCadiz.TDTChannelsEPG">
    <title lang="es">Noticias OC</title>
    <desc lang="es">Desde Onda Cádiz Televisión, ofrecemos a nuestros espectadores, la posibilidad de que puedan tomar, con nosotros, el pulso diario de nuestra ciudad. Política, cultura, sucesos, ocio, deportes, información meteorológica y toda la información puntual que genera nuestra ciudad, con el máximo rigor y pluralidad que debe de tener una televisión municipal.</desc>
    <icon src="http://tv.ocadizdigital.es/sites/default/files/styles/ancho-350/public/imagenes_programas/noticias_cadiz.jpg?itok=N_oSD2Vc" />
  </programme>
  <programme start="20200124013000 +0100" stop="20200124020000 +0100" channel="OndaCadiz.TDTChannelsEPG">
    <title lang="es">La levantá</title>
    <desc lang="es">Programa dedicado en exclusividad a la Semana Santa gaditana y todo lo relacionado con la misma. Hermandades y Cofradías, salidas procesionales, cultos y distintas actividades, son tratados en formatos de entrevistas, tertulias y reportajes. Mayte Huguet es el encargo de dar forma a este espacio televisivo.</desc>
    <icon src="http://tv.ocadizdigital.es/sites/default/files/styles/ancho-350/public/imagenes_programas/la_levanta.jpg?itok=j694IFE6" />
  </programme>
  <programme start="20200124020000 +0100" stop="20200124040000 +0100" channel="OndaCadiz.TDTChannelsEPG">
    <title lang="es">El mirador - noticias</title>
    <desc lang="es">Primera parte del Magazine el Mirador con un marcado carácter informativo.
La iniciamos asomándonos a la previsión meteorológica y a las portadas del día de los principales periódicos locales y nacionales, para seguidamente repasar las noticias más destacadas ofrecidas por los servicios informativos de Onda Cádiz Tv.
A continuación, espacio para el Debate y el intercambio de opiniones e ideas en la  tertulia de actualidad. Sociedad, política, economía, cultura, costumbres y demás aspectos de interés con la mirada puesta principalmente en las cuestiones que más afectan a nuestra capital, nuestra Bahía y nuestra provincia.
Esta primera parte del Mirador se remata con una encuentro con las Instituciones públicas, Colegios profesionales, asociaciones del ámbito de la  empresa, Universidad, Cuerpos y Fuerzas Seguridad y demás organismos públicos y privados en una entrevista de actualidad.</desc>
    <icon src="http://tv.ocadizdigital.es/sites/default/files/styles/ancho-350/public/imagenes_programas/logo_el_mirador_boton_noticias.jpg?itok=i43Wib16" />
  </programme>
  <programme start="20200124040000 +0100" stop="20200124043000 +0100" channel="OndaCadiz.TDTChannelsEPG">
    <title lang="es">Traspunte</title>
    <desc lang="es">Programa de televisión donde hablamos de Cultura, desde la pasión que nos inspiran: la literatura, el teatro, la música, el arte, la danza y todas las disciplinas artísticas que tengan algo que decir en Cádiz. La actualidad y los protagonistas de la agenda cultural, tienen cabida en Traspunte, presentado por Almudena de la Montaña.</desc>
    <icon src="http://tv.ocadizdigital.es/sites/default/files/styles/ancho-350/public/imagenes_programas/traspunte.jpg?itok=y2kTTmMd" />
  </programme>
  <programme start="20200124043000 +0100" stop="20200124073000 +0100" channel="OndaCadiz.TDTChannelsEPG">
    <title lang="es">Fin emisión</title>
    <icon src="http://tv.ocadizdigital.es/sites/default/files/styles/ancho-350/public/imagenes_programas/ondacadiz_logo-1escalado_3.png?itok=V3zle7Kq" />
  </programme>
  <programme start="20200124073000 +0100" stop="20200124090000 +0100" channel="OndaCadiz.TDTChannelsEPG">
    <title lang="es">Las ma\u00f1anas del Falla</title>
    <icon src="https://carnavaldecadiztv.com/wp-content/uploads/2019/08/coac-2020.jpg" />
  </programme>
  <programme start="20200124090000 +0100" stop="20200124103000 +0100" channel="OndaCadiz.TDTChannelsEPG">
    <title lang="es">El mirador - noticias</title>
    <desc lang="es">Primera parte del Magazine el Mirador con un marcado carácter informativo.
La iniciamos asomándonos a la previsión meteorológica y a las portadas del día de los principales periódicos locales y nacionales, para seguidamente repasar las noticias más destacadas ofrecidas por los servicios informativos de Onda Cádiz Tv.
A continuación, espacio para el Debate y el intercambio de opiniones e ideas en la  tertulia de actualidad. Sociedad, política, economía, cultura, costumbres y demás aspectos de interés con la mirada puesta principalmente en las cuestiones que más afectan a nuestra capital, nuestra Bahía y nuestra provincia.
Esta primera parte del Mirador se remata con una encuentro con las Instituciones públicas, Colegios profesionales, asociaciones del ámbito de la  empresa, Universidad, Cuerpos y Fuerzas Seguridad y demás organismos públicos y privados en una entrevista de actualidad.</desc>
    <icon src="http://tv.ocadizdigital.es/sites/default/files/styles/ancho-350/public/imagenes_programas/logo_el_mirador_boton_noticias.jpg?itok=i43Wib16" />
  </programme>
  <programme start="20200124103000 +0100" stop="20200124110000 +0100" channel="OndaCadiz.TDTChannelsEPG">
    <title lang="es">El mirador - social</title>
    <desc lang="es">Enrique Miranda y Anabel Flores les invitan a este espacio de entretenimiento de dos horas en directo dedicado a la actualidad y eventos destacados en la ciudad. Música, moda, espectáculos, flamenco, gastronomía, asociaciones y entidades solidarias visitarán nuestro plató para compartir sus proyectos. Asómense al Mirador Magazine para descubrir Cádiz y su faceta más artística y cultural.</desc>
    <icon src="http://tv.ocadizdigital.es/sites/default/files/styles/ancho-350/public/imagenes_programas/logo_el_mirador_boton_social.jpg?itok=d7lUUMa8" />
  </programme>
  <programme start="20200124110000 +0100" stop="20200124113000 +0100" channel="OndaCadiz.TDTChannelsEPG">
    <title lang="es">Saludablemente</title>
    <desc lang="es">Onda Cádiz televisión estrena programa sobre Salud y Bienestar.
“Saludablemente” es un nuevo espacio con reportajes y entrevistas en distinto formato con el objetivo de aportar opciones para mejorar la calidad de vida de nuestros televidentes.
Contaremos con profesionales acreditados para aportar sus conocimientos y valoraciones. Secciones como “Tecnologías para la Salud”, “Actualidad”, “Sexo y Salud”, “Mente Sana”, “Nutrición” y “Ocio Saludable” irán añadiendo contenidos de interés, en un espacio con una hora de duración.
“Saludablemente” estará en sus casas a través de su televisión municipal cada semana, los sábados a las 21:30 horas, conducido por la periodista y redactora de informativos de esta casa, Fátima Sánchez.</desc>
    <icon src="http://tv.ocadizdigital.es/sites/default/files/styles/ancho-350/public/imagenes_programas/saludablemente_logo.jpg?itok=cyhfz8yd" />
  </programme>
  <programme start="20200124113000 +0100" stop="20200124130000 +0100" channel="OndaCadiz.TDTChannelsEPG">
    <title lang="es">Las ma\u00f1anas del Falla</title>
    <icon src="https://carnavaldecadiztv.com/wp-content/uploads/2019/08/coac-2020.jpg" />
  </programme>
  <programme start="20200124130000 +0100" stop="20200124133000 +0100" channel="OndaCadiz.TDTChannelsEPG">
    <title lang="es">Carnaval a\u00f1ejo</title>
    <icon src="https://carnavaldecadiztv.com/wp-content/uploads/2019/08/coac-2020.jpg" />
  </programme>
  <programme start="20200124133000 +0100" stop="20200124140000 +0100" channel="OndaCadiz.TDTChannelsEPG">
    <title lang="es">Noticias OC 1ª Edición</title>
    <desc lang="es">Desde Onda Cádiz Televisión, ofrecemos a nuestros espectadores, la posibilidad de que puedan tomar, con nosotros, el pulso diario de nuestra ciudad. Política, cultura, sucesos, ocio, deportes, información meteorológica y toda la información puntual que genera nuestra ciudad, con el máximo rigor y pluralidad que debe de tener una televisión municipal.</desc>
    <icon src="http://tv.ocadizdigital.es/sites/default/files/styles/ancho-350/public/imagenes_programas/noticias_cadiz.jpg?itok=N_oSD2Vc" />
  </programme>
  <programme start="20200124140000 +0100" stop="20200124190000 +0100" channel="OndaCadiz.TDTChannelsEPG">
    <title lang="es">COAC 2020</title>
    <desc lang="es">Comparsa Los Caricatos 
Horacio Calvillo – En 2019: La Bella y la Bestia (Ronda)

Comparsa Oh capitán, my capitán 
Constantino Tovar Verdejo – Tercer premio en 2018: Tic-Tac, Tic-Tac (Cádiz)

Cabeza de serie: Coro Las Creaciones S.A. 
Nandi Migueles – En 2019: Ópera Cádiz (Cádiz)

Chirigota El de las llaves con sus muertos 
F. Javier Fuentes – Cádiz

Comparsa La superviviente

Chirigota Las eventuales

Comparsa Los Traicioneros 
L. Miguel Cobos y Marcelo Cobos – En 2019: Los mequetrefes (Córdoba).</desc>
    <icon src="https://carnavaldecadiztv.com/wp-content/uploads/2019/08/coac-2020.jpg" />
  </programme>
  <programme start="20200124190000 +0100" stop="20200124193000 +0100" channel="OndaCadiz.TDTChannelsEPG">
    <title lang="es">Noticias OC</title>
    <desc lang="es">Desde Onda Cádiz Televisión, ofrecemos a nuestros espectadores, la posibilidad de que puedan tomar, con nosotros, el pulso diario de nuestra ciudad. Política, cultura, sucesos, ocio, deportes, información meteorológica y toda la información puntual que genera nuestra ciudad, con el máximo rigor y pluralidad que debe de tener una televisión municipal.</desc>
    <icon src="http://tv.ocadizdigital.es/sites/default/files/styles/ancho-350/public/imagenes_programas/noticias_cadiz.jpg?itok=N_oSD2Vc" />
  </programme>
  <programme start="20200124193000 +0100" stop="20200125010000 +0100" channel="OndaCadiz.TDTChannelsEPG">
    <title lang="es">COAC 2020</title>
    <desc lang="es">Chirigota Chernobyl El Musical
Antonio Pedro Serrano ‘El Canijo’ y Jesús Bienvenido – En 2018: Qué caló (Cádiz)


Cabeza de serie: Coro Manos Arriba 
Valdés, Cesario López y José María Barranco – En 2019: Siguiendo tus pasos, Cádiz (Cádiz)

Chirigota Marilo’s
M. Ángel Gómez y David Gómez – Carmona


Comparsa La culpa es mía 
L. Manuel Ripoll – Sevilla

Cuarteto Cari, resiste 
Javi Aguilera ‘Canijo’, F. José Fernández y Ángel Piulestán – En 2018: Los de la gran puñeta (Cádiz)

Chirigota Los Joaquín Dead 
Jesús Montero y Rafael Fernández – En 2019: El sábado me lo trago enterito y el domingo repito (San Fernando)

Comparsa Mataero 
A. Manuel Cruz y Andrés Morales – Cádiz.</desc>
    <icon src="https://carnavaldecadiztv.com/wp-content/uploads/2019/08/coac-2020.jpg" />
  </programme>
  <programme start="20200125010000 +0100" stop="20200125013000 +0100" channel="OndaCadiz.TDTChannelsEPG">
    <title lang="es">Noticias OC</title>
    <desc lang="es">Desde Onda Cádiz Televisión, ofrecemos a nuestros espectadores, la posibilidad de que puedan tomar, con nosotros, el pulso diario de nuestra ciudad. Política, cultura, sucesos, ocio, deportes, información meteorológica y toda la información puntual que genera nuestra ciudad, con el máximo rigor y pluralidad que debe de tener una televisión municipal.</desc>
    <icon src="http://tv.ocadizdigital.es/sites/default/files/styles/ancho-350/public/imagenes_programas/noticias_cadiz.jpg?itok=N_oSD2Vc" />
  </programme>
  <programme start="20200125013000 +0100" stop="20200125020000 +0100" channel="OndaCadiz.TDTChannelsEPG">
    <title lang="es">Traspunte</title>
    <desc lang="es">Programa de televisión donde hablamos de Cultura, desde la pasión que nos inspiran: la literatura, el teatro, la música, el arte, la danza y todas las disciplinas artísticas que tengan algo que decir en Cádiz. La actualidad y los protagonistas de la agenda cultural, tienen cabida en Traspunte, presentado por Almudena de la Montaña.</desc>
    <icon src="http://tv.ocadizdigital.es/sites/default/files/styles/ancho-350/public/imagenes_programas/traspunte.jpg?itok=y2kTTmMd" />
  </programme>
  <programme start="20200125020000 +0100" stop="20200125040000 +0100" channel="OndaCadiz.TDTChannelsEPG">
    <title lang="es">El mirador - noticias</title>
    <desc lang="es">Primera parte del Magazine el Mirador con un marcado carácter informativo.
La iniciamos asomándonos a la previsión meteorológica y a las portadas del día de los principales periódicos locales y nacionales, para seguidamente repasar las noticias más destacadas ofrecidas por los servicios informativos de Onda Cádiz Tv.
A continuación, espacio para el Debate y el intercambio de opiniones e ideas en la  tertulia de actualidad. Sociedad, política, economía, cultura, costumbres y demás aspectos de interés con la mirada puesta principalmente en las cuestiones que más afectan a nuestra capital, nuestra Bahía y nuestra provincia.
Esta primera parte del Mirador se remata con una encuentro con las Instituciones públicas, Colegios profesionales, asociaciones del ámbito de la  empresa, Universidad, Cuerpos y Fuerzas Seguridad y demás organismos públicos y privados en una entrevista de actualidad.</desc>
    <icon src="http://tv.ocadizdigital.es/sites/default/files/styles/ancho-350/public/imagenes_programas/logo_el_mirador_boton_noticias.jpg?itok=i43Wib16" />
  </programme>
  <programme start="20200125040000 +0100" stop="20200125043000 +0100" channel="OndaCadiz.TDTChannelsEPG">
    <title lang="es">Saludablemente</title>
    <desc lang="es">Onda Cádiz televisión estrena programa sobre Salud y Bienestar.
“Saludablemente” es un nuevo espacio con reportajes y entrevistas en distinto formato con el objetivo de aportar opciones para mejorar la calidad de vida de nuestros televidentes.
Contaremos con profesionales acreditados para aportar sus conocimientos y valoraciones. Secciones como “Tecnologías para la Salud”, “Actualidad”, “Sexo y Salud”, “Mente Sana”, “Nutrición” y “Ocio Saludable” irán añadiendo contenidos de interés, en un espacio con una hora de duración.
“Saludablemente” estará en sus casas a través de su televisión municipal cada semana, los sábados a las 21:30 horas, conducido por la periodista y redactora de informativos de esta casa, Fátima Sánchez.</desc>
    <icon src="http://tv.ocadizdigital.es/sites/default/files/styles/ancho-350/public/imagenes_programas/saludablemente_logo.jpg?itok=cyhfz8yd" />
  </programme>
  <programme start="20200125043000 +0100" stop="20200125073000 +0100" channel="OndaCadiz.TDTChannelsEPG">
    <title lang="es">Fin emisión</title>
    <icon src="http://tv.ocadizdigital.es/sites/default/files/styles/ancho-350/public/imagenes_programas/ondacadiz_logo-1escalado_3.png?itok=V3zle7Kq" />
  </programme>
  <programme start="20200125073000 +0100" stop="20200125090000 +0100" channel="OndaCadiz.TDTChannelsEPG">
    <title lang="es">Las ma\u00f1anas del Falla</title>
    <icon src="https://carnavaldecadiztv.com/wp-content/uploads/2019/08/coac-2020.jpg" />
  </programme>
  <programme start="20200125090000 +0100" stop="20200125120000 +0100" channel="OndaCadiz.TDTChannelsEPG">
    <title lang="es">COAC 2020</title>
    <icon src="https://carnavaldecadiztv.com/wp-content/uploads/2019/08/coac-2020.jpg" />
  </programme>
  <programme start="20200125120000 +0100" stop="20200125140000 +0100" channel="OndaCadiz.TDTChannelsEPG">
    <title lang="es">Historias del carnaval</title>
    <icon src="https://carnavaldecadiztv.com/wp-content/uploads/2019/08/coac-2020.jpg" />
  </programme>
  <programme start="20200125140000 +0100" stop="20200125190000 +0100" channel="OndaCadiz.TDTChannelsEPG">
    <title lang="es">COAC 2020</title>
    <desc lang="es">Chirigota Chernobyl El Musical
Antonio Pedro Serrano ‘El Canijo’ y Jesús Bienvenido – En 2018: Qué caló (Cádiz)


Cabeza de serie: Coro Manos Arriba 
Valdés, Cesario López y José María Barranco – En 2019: Siguiendo tus pasos, Cádiz (Cádiz)

Chirigota Marilo’s
M. Ángel Gómez y David Gómez – Carmona


Comparsa La culpa es mía 
L. Manuel Ripoll – Sevilla

Cuarteto Cari, resiste 
Javi Aguilera ‘Canijo’, F. José Fernández y Ángel Piulestán – En 2018: Los de la gran puñeta (Cádiz)

Chirigota Los Joaquín Dead 
Jesús Montero y Rafael Fernández – En 2019: El sábado me lo trago enterito y el domingo repito (San Fernando)

Comparsa Mataero 
A. Manuel Cruz y Andrés Morales – Cádiz.</desc>
    <icon src="https://carnavaldecadiztv.com/wp-content/uploads/2019/08/coac-2020.jpg" />
  </programme>
  <programme start="20200125190000 +0100" stop="20200125193000 +0100" channel="OndaCadiz.TDTChannelsEPG">
    <title lang="es">Noticias cinco días</title>
    <icon src="https://carnavaldecadiztv.com/wp-content/uploads/2019/08/coac-2020.jpg" />
  </programme>
  <programme start="20200125193000 +0100" stop="20200126010000 +0100" channel="OndaCadiz.TDTChannelsEPG">
    <title lang="es">COAC 2020</title>
    <desc lang="es">Chirigota Los del corazón partío 
Ican Herrera, J. Miguel Villegas, J. María Barranco y A. José Caballero – Cádiz

Comparsa El trovador

Chirigota Pídeme lo que tú quieras 
Francisco Macías y Manuel Benítez – En 2019: Los Morossos (Chiclana)

Comparsa Vengo a por ti 
F. Javier Belizon – En 2019: No es país para cuerdo San Fernando

Chirigota Los 7 locos 
David Amaya – En 2019: Los Pecaores Capitales (Cádiz)

Cabeza de serie: Coro Tocamé 
Julio Pardo y Canijo – En 2019: El Batallitas (Cádiz)

Comparsa El cascarrabias ‘Cuento de carnaval’ 
J. Manuel Pérez y J. Ricardo Pérez – Sanlúcar de Barrameda.</desc>
    <icon src="https://carnavaldecadiztv.com/wp-content/uploads/2019/08/coac-2020.jpg" />
  </programme>
  <programme start="20200126010000 +0100" stop="20200126013000 +0100" channel="OndaCadiz.TDTChannelsEPG">
    <title lang="es">Noticias OC</title>
    <desc lang="es">Desde Onda Cádiz Televisión, ofrecemos a nuestros espectadores, la posibilidad de que puedan tomar, con nosotros, el pulso diario de nuestra ciudad. Política, cultura, sucesos, ocio, deportes, información meteorológica y toda la información puntual que genera nuestra ciudad, con el máximo rigor y pluralidad que debe de tener una televisión municipal.</desc>
    <icon src="http://tv.ocadizdigital.es/sites/default/files/styles/ancho-350/public/imagenes_programas/noticias_cadiz.jpg?itok=N_oSD2Vc" />
  </programme>
  <programme start="20200126013000 +0100" stop="20200126020000 +0100" channel="OndaCadiz.TDTChannelsEPG">
    <title lang="es">Saludablemente</title>
    <desc lang="es">Onda Cádiz televisión estrena programa sobre Salud y Bienestar.
“Saludablemente” es un nuevo espacio con reportajes y entrevistas en distinto formato con el objetivo de aportar opciones para mejorar la calidad de vida de nuestros televidentes.
Contaremos con profesionales acreditados para aportar sus conocimientos y valoraciones. Secciones como “Tecnologías para la Salud”, “Actualidad”, “Sexo y Salud”, “Mente Sana”, “Nutrición” y “Ocio Saludable” irán añadiendo contenidos de interés, en un espacio con una hora de duración.
“Saludablemente” estará en sus casas a través de su televisión municipal cada semana, los sábados a las 21:30 horas, conducido por la periodista y redactora de informativos de esta casa, Fátima Sánchez.</desc>
    <icon src="http://tv.ocadizdigital.es/sites/default/files/styles/ancho-350/public/imagenes_programas/saludablemente_logo.jpg?itok=cyhfz8yd" />
  </programme>
  <programme start="20200126020000 +0100" stop="20200126040000 +0100" channel="OndaCadiz.TDTChannelsEPG">
    <title lang="es">Historias del carnaval</title>
    <icon src="https://carnavaldecadiztv.com/wp-content/uploads/2019/08/coac-2020.jpg" />
  </programme>
  <programme start="20200126040000 +0100" stop="20200126043000 +0100" channel="OndaCadiz.TDTChannelsEPG">
    <title lang="es">Noticias cinco días</title>
    <icon src="https://carnavaldecadiztv.com/wp-content/uploads/2019/08/coac-2020.jpg" />
  </programme>
  <programme start="20200126043000 +0100" stop="20200126073000 +0100" channel="OndaCadiz.TDTChannelsEPG">
    <title lang="es">Fin emisión</title>
    <icon src="http://tv.ocadizdigital.es/sites/default/files/styles/ancho-350/public/imagenes_programas/ondacadiz_logo-1escalado_3.png?itok=V3zle7Kq" />
  </programme>
  <programme start="20200126073000 +0100" stop="20200126081500 +0100" channel="OndaCadiz.TDTChannelsEPG">
    <title lang="es">Noticias cinco días</title>
    <icon src="https://carnavaldecadiztv.com/wp-content/uploads/2019/08/coac-2020.jpg" />
  </programme>
  <programme start="20200126081500 +0100" stop="20200126090000 +0100" channel="OndaCadiz.TDTChannelsEPG">
    <title lang="es">Zona Historia</title>
    <desc lang="es">La Historia de Cádiz de la mano de Salvador Santos.</desc>
    <icon src="http://tv.ocadizdigital.es/sites/default/files/styles/ancho-350/public/imagenes_programas/zona-historia.jpg?itok=DjS8EbIA" />
  </programme>
  <programme start="20200126090000 +0100" stop="20200126120000 +0100" channel="OndaCadiz.TDTChannelsEPG">
    <title lang="es">COAC 2020</title>
    <icon src="https://carnavaldecadiztv.com/wp-content/uploads/2019/08/coac-2020.jpg" />
  </programme>
  <programme start="20200126120000 +0100" stop="20200126140000 +0100" channel="OndaCadiz.TDTChannelsEPG">
    <title lang="es">Historias del carnaval</title>
    <icon src="https://carnavaldecadiztv.com/wp-content/uploads/2019/08/coac-2020.jpg" />
  </programme>
  <programme start="20200126140000 +0100" stop="20200126190000 +0100" channel="OndaCadiz.TDTChannelsEPG">
    <title lang="es">COAC 2020</title>
    <desc lang="es">Chirigota Los del corazón partío 
Ican Herrera, J. Miguel Villegas, J. María Barranco y A. José Caballero – Cádiz

Comparsa El trovador

Chirigota Pídeme lo que tú quieras 
Francisco Macías y Manuel Benítez – En 2019: Los Morossos (Chiclana)

Comparsa Vengo a por ti 
F. Javier Belizon – En 2019: No es país para cuerdo San Fernando

Chirigota Los 7 locos 
David Amaya – En 2019: Los Pecaores Capitales (Cádiz)

Cabeza de serie: Coro Tocamé 
Julio Pardo y Canijo – En 2019: El Batallitas (Cádiz)

Comparsa El cascarrabias ‘Cuento de carnaval’ 
J. Manuel Pérez y J. Ricardo Pérez – Sanlúcar de Barrameda.</desc>
    <icon src="https://carnavaldecadiztv.com/wp-content/uploads/2019/08/coac-2020.jpg" />
  </programme>
  <programme start="20200126190000 +0100" stop="20200126193000 +0100" channel="OndaCadiz.TDTChannelsEPG">
    <title lang="es">Noticias cinco días</title>
    <icon src="https://carnavaldecadiztv.com/wp-content/uploads/2019/08/coac-2020.jpg" />
  </programme>
  <programme start="20200126193000 +0100" stop="20200127010000 +0100" channel="OndaCadiz.TDTChannelsEPG">
    <title lang="es">COAC 2020</title>
    <desc lang="es">Cuarteto Merda, merda, mucha merda 
Álvaro Galán – El Puerto de Santa María

Coro Rayadillo 
Paco Melero y José Antonio Montiel – Nueva agrupación (Chiclana)

Chirigota Habla que te veo 
J. Manuel Bonfante – Cádiz

Comparsa Mala vida 
Raúl Sánchez – Las Cabezas de San Juan (Sevilla)

Chirigota Misión Imposible 
J. Manuel Santos, Rafael Valero, F. Javier Díaz – En 2019: Los que vienen de etiqueta – Cádiz

Cabeza de serie: Comparsa Los Salvajes 
F. Javier Ramírez ‘Chato’ y Tomy Alemania – En 2019: La Mananda (Cádiz).</desc>
    <icon src="https://carnavaldecadiztv.com/wp-content/uploads/2019/08/coac-2020.jpg" />
  </programme>
</tv>